MANIFEST.in
README.rst
setup.py
verobject.py
./verobject.py
verobject.egg-info/PKG-INFO
verobject.egg-info/SOURCES.txt
verobject.egg-info/dependency_links.txt
verobject.egg-info/requires.txt
verobject.egg-info/top_level.txt