Metadata-Version: 1.0
Name: verobject
Version: 0.1.4
Summary: Version controlled object database on Redis
Home-page: https://github.com/jart/verobject
Author: Justine Tunney
Author-email: jtunney@lobstertech.com
License: MIT
Platform: UNKNOWN
Classifier: Development Status :: 5 - Production/Stable
Classifier: License :: OSI Approved :: MIT License
Classifier: Intended Audience :: Developers
Classifier: Programming Language :: Python
Classifier: Topic :: Database
